[{"id":"6287784995491@s.whatsapp.net","name":"私は愛してる","time":"20:37:12 WIB","serial":"2c019f608f8803475e8c"},{"id":"6281990220985@s.whatsapp.net","name":"orng","time":"20:37:12 WIB","serial":"aea90a02cc2cbf896442"},{"id":"6283176664010@s.whatsapp.net","name":"ㅤㅤㅤㅤㅤㅤㅤㅤ","time":"20:37:12 WIB","serial":"61f21d55e76f704623ad"},{"id":"6289601115281@s.whatsapp.net","name":"cca","time":"20:37:12 WIB","serial":"5c339495a1ce3aeb2b70"},{"id":"6283135308236@s.whatsapp.net","name":"Bot Brey","time":"20:37:12 WIB","serial":"84ccc582adea21d905f2"},{"id":"6281338370197@s.whatsapp.net","name":"Febb","time":"20:37:12 WIB","serial":"2d0b1cf637e50b2dd0bd"},{"id":"6281262399756@s.whatsapp.net","name":"Cez","time":"20:37:12 WIB","serial":"0add9fd7ef32276f6b5c"},{"id":"6289684570475@s.whatsapp.net","name":"ㅤㅤ","time":"20:37:12 WIB","serial":"adb79e0479970c2be249"},{"id":"6285785694474@s.whatsapp.net","name":"匚卂ㄥㄥ  爪乇  卂ㄥ|几乇","time":"20:37:12 WIB","serial":"6854fe77605cf135c546"},{"id":"94716545508@s.whatsapp.net","name":"Chalaka Sandepa","time":"20:37:12 WIB","serial":"d249e62a9b957aaa8d63"},{"id":"6287735482233@s.whatsapp.net","name":"-","time":"20:37:12 WIB","serial":"1bf121071c003e3fba69"},{"id":"62881037056345@s.whatsapp.net","name":"~RczlF","time":"20:37:12 WIB","serial":"c1161d6c4270cc42d2fb"},{"id":"94772884023@s.whatsapp.net","name":"SR","time":"20:37:12 WIB","serial":"32c9a2d81016cc9e1f33"},{"id":"6285830036793@s.whatsapp.net","name":"🤫","time":"21:57:21 WIB","serial":"18c35696b6964e8d3816"},{"id":"59162820548@s.whatsapp.net","name":"حًمط:)","time":"22:23:33 WIB","serial":"4bb6b76072b36e770150"},{"id":"6283838715651@s.whatsapp.net","name":"3i674","time":"22:39:32 WIB","serial":"486e2036ac4b4b4f84b5"},{"id":"6281258775824@s.whatsapp.net","name":"ucii","time":"22:39:32 WIB","serial":"d0baa3a9c92d02e197c7"},{"id":"6281379122802@s.whatsapp.net","name":"Rezza Botz","time":"22:39:32 WIB","serial":"9a3e7cb774b03b934f22"},{"id":"6287782663873@s.whatsapp.net","name":"?ナフィザ・アイラ・プトゥリ","time":"22:39:32 WIB","serial":"06602ede41e8dbbb8191"},{"id":"6281515696780@s.whatsapp.net","name":"I'm back","time":"22:39:32 WIB","serial":"fa923d23fbada09542aa"},{"id":"6288216998191@s.whatsapp.net","name":"ㅤㅤ","time":"22:56:00 WIB","serial":"b83b3462bed18c8a2a72"},{"id":"6285805120213@s.whatsapp.net","name":"ONETWO 7/19 <3","time":"22:56:00 WIB","serial":"015196e9e6c9cddcb0ad"},{"id":"6281290895375@s.whatsapp.net","name":"eshx","time":"22:56:00 WIB","serial":"dc26d7098bb59eb132c0"},{"id":"6282125163976@s.whatsapp.net","name":"-","time":"22:56:00 WIB","serial":"4fb01a07f72c67e3c3aa"},{"id":"6285791020103@s.whatsapp.net","name":"~ziz","time":"22:56:00 WIB","serial":"7a4c3620457918f0f608"},{"id":"6285606026250@s.whatsapp.net","name":",","time":"22:56:00 WIB","serial":"6d2be5204e7b49d0134b"},{"id":"62895334930508@s.whatsapp.net","name":".","time":"23:51:16 WIB","serial":"4381ebc597976d427c9a"},{"id":"62882001113526@s.whatsapp.net","name":".","time":"23:51:16 WIB","serial":"e46cd84b2e759f0cd303"},{"id":"6283195509924@s.whatsapp.net","name":"Yandatau","time":"23:51:16 WIB","serial":"c4c81ab90d30827b3968"},{"id":"94789481495@s.whatsapp.net","name":"ẉa.me/ꪶ𝐈̱_𝐀̲𝐌̱_𝐍̱𝐎̱𝐓̱_𝐇𝐈𝐌","time":"12:06:21 WIB","serial":"2ad0c690949aea88f2df"},{"id":"6281809086997@s.whatsapp.net","name":"Atomic Habbit","time":"15:02:12 WIB","serial":"c110c372f7f115a517d1"},{"id":"6289509348314@s.whatsapp.net","name":"P","time":"19:29:23 WIB","serial":"530edf697a3d27c73d71"},{"id":"918129856593@s.whatsapp.net","name":"ᴜᴍᴍᴀ|| ᴜʏɪʀ♥️","time":"19:29:23 WIB","serial":"c116f794dd62400a7fcc"},{"id":"6281993182063@s.whatsapp.net","name":"Andika","time":"19:29:23 WIB","serial":"f75d79c8f3cff6cb2f31"},{"id":"94775362291@s.whatsapp.net","name":"Hiruja hasal","time":"19:29:23 WIB","serial":"ee5f990c95a677316c0d"},{"id":"94785137394@s.whatsapp.net","name":"✎⃖n⃖o⃖t⃖e🐰̷ཽ̳ˢཽᵘ⃒ᵈ⃖ᵈ⃖ᵃ™̷⚠","time":"19:29:23 WIB","serial":"dda3e3e861ff8ece66b3"},{"id":"6282114432081@s.whatsapp.net","name":"Kamuu😭","time":"20:06:22 WIB","serial":"c13db58ab463a44ddfc7"},{"id":"60172191766@s.whatsapp.net","name":"Turu","time":"20:06:22 WIB","serial":"993c1cfa34929962b1f1"},{"id":"6289508801985@s.whatsapp.net","name":"🌸 𝐗𝐄𝐑𝐄𝐂𝐀 𝐃𝐀 𝐋𝐔𝐙 🌸 ‎‏‎‏‎‏‎","time":"20:06:22 WIB","serial":"4244795dd0ff4abe9c44"},{"id":"6281390506259@s.whatsapp.net","name":"~Panggil Aja Wildanᥫ᭡","time":"20:56:51 WIB","serial":"b35796d834d37ab224f7"},{"id":"94703261353@s.whatsapp.net","name":"💗😊චබී😊💗","time":"21:00:30 WIB","serial":"4c71180c87c627486bd3"},{"id":"6285380099349@s.whatsapp.net","name":"And 🫥","time":"21:00:30 WIB","serial":"8cae79aa0a4d25edfb22"},{"id":"62895323214364@s.whatsapp.net","name":"KSZ","time":"21:00:30 WIB","serial":"c9a94462657c31419ff6"},{"id":"94741021543@s.whatsapp.net","name":"SENAL","time":"21:00:30 WIB","serial":"5972a1da4159840c2004"},{"id":"94773909379@s.whatsapp.net","name":"꧁⃝Ｓᴸ̶͢ ᴼ̶ʟ̳⃔ᴅ Ꮳᴴ̶͢ᵁᎢ̶⃕Ꮖ꧂⁩","time":"21:00:30 WIB","serial":"1d2595ef320f9467bedc"},{"id":"94721309211@s.whatsapp.net","name":"☞ᵃ☜","time":"21:11:00 WIB","serial":"b5291acf3ada1ab111fa"},{"id":"94721309211@s.whatsapp.net","name":"☞ᵃ☜","time":"21:11:00 WIB","serial":"07a12da4cd5016a14ad5"},{"id":"917594956658@s.whatsapp.net","name":"LOD-BILAL!!!","time":"21:11:00 WIB","serial":"ee40656889f24536cabd"},{"id":"62895367083015@s.whatsapp.net","name":"Gak Tau.","time":"21:21:26 WIB","serial":"5c5a4a56506e37fde92e"},{"id":"6282271359497@s.whatsapp.net","name":"カダフィ","time":"21:21:26 WIB","serial":"ad90910ef2702b8cba8d"},{"id":"62895635658560@s.whatsapp.net","name":"azizfajar🗿","time":"21:21:26 WIB","serial":"0fbd9e660e4197e01513"},{"id":"94778055251@s.whatsapp.net","name":"ＳＲ","time":"21:29:54 WIB","serial":"2c852a01e0a846237f95"},{"id":"94714841631@s.whatsapp.net","name":"Chanuka 😄","time":"21:29:54 WIB","serial":"e1963d79202370a5146e"},{"id":"94705792134@s.whatsapp.net","name":"𝗧𝗛𝗔𝗥𝗨𝗦𝗛𝗔 𝗔𝗗𝗜𝗧𝗛𝗬𝗔","time":"21:29:54 WIB","serial":"756d7a52c9488d7764ad"},{"id":"94719203682@s.whatsapp.net","name":"Tharush","time":"21:29:54 WIB","serial":"d74d5d98935cbc8775ac"},{"id":"94704209801@s.whatsapp.net","name":"Prabodha Prashad malinga","time":"21:45:05 WIB","serial":"b24cf2d1c36f766ca29a"},{"id":"94741446105@s.whatsapp.net","name":"-","time":"21:45:05 WIB","serial":"d89e4603b64ba90cae97"},{"id":"212630843609@s.whatsapp.net","name":"𝚃𝚊𝚏𝚒𝚑 / 𝙾𝚏𝚏𝚒𝚌 𓂉","time":"21:45:05 WIB","serial":"2f643d22b3579cc4c5e5"},{"id":"94772985525@s.whatsapp.net","name":"꧁₭ɪɴ⃮ɢ⃔⃟⃮ සᶜʰⁱ⃯යා⃯⃟ʰ꧂","time":"21:45:05 WIB","serial":"0ddf9ec687e83130be2d"},{"id":"94722251881@s.whatsapp.net","name":"-","time":"21:53:58 WIB","serial":"04c33959998402c18f63"},{"id":"94755517903@s.whatsapp.net","name":"Kaushan","time":"21:53:58 WIB","serial":"24120fb01acc2990aa94"},{"id":"94773598112@s.whatsapp.net","name":"💞Hiranaya💞","time":"22:02:50 WIB","serial":"7eaba78adba8f192df46"},{"id":"94775731839@s.whatsapp.net","name":"ᛕᗩᐯIᑎᗪᑌ ᑎᗩᐯᗝᗪ🍁🔥","time":"22:07:23 WIB","serial":"4d3aa09578a6474236c3"},{"id":"94704209229@s.whatsapp.net","name":"Himaya Piyunethni","time":"22:07:23 WIB","serial":"f53d1fa469c0d28baf9b"},{"id":"6283834645903@s.whatsapp.net","name":"Bot-Brey","time":"00:00:06 WIB","serial":"691db134007ab8ddc48a"}]